xul/__init__.py
xul/etree.py
xul/ppxml.py
xul/py.typed
xul/utils.py
xul/validate.py
xul/xpath.py
xul/xsl.py
xul/cmd/__init__.py
xul/cmd/ppx.py
xul/cmd/transform.py
xul/cmd/validate.py
xul/cmd/xp.py
xul-3.1.1.dist-info/METADATA
xul-3.1.1.dist-info/WHEEL
xul-3.1.1.dist-info/entry_points.txt
xul-3.1.1.dist-info/licenses/LICENSE.txt
xul-3.1.1.dist-info/RECORD
