Metadata-Version: 2.4
Name: Xul
Version: 3.1.1
Summary: XML (XPath, XSD, XSLT) Utilities
Project-URL: Homepage, https://xul.readthedocs.io/
Project-URL: Documentation, https://xul.readthedocs.io/en/stable/
Project-URL: Changelog, https://xul.readthedocs.io/en/latest/changelog.html
Project-URL: Source, https://github.com/peteradrichem/Xul
Author-email: Peter Adrichem <Peter.Adrichem@gmail.com>
License-Expression: MIT
License-File: LICENSE.txt
Keywords: dtd,relax ng,rng,xml,xml schema,xpath,xsd,xslt
Classifier: Development Status :: 5 - Production/Stable
Classifier: Environment :: Console
Classifier: Operating System :: OS Independent
Classifier: Programming Language :: Python
Classifier: Programming Language :: Python :: 3.9
Classifier: Programming Language :: Python :: 3.10
Classifier: Programming Language :: Python :: 3.11
Classifier: Programming Language :: Python :: 3.12
Classifier: Programming Language :: Python :: 3.13
Classifier: Programming Language :: Python :: 3.14
Classifier: Programming Language :: Python :: Implementation :: CPython
Classifier: Topic :: Text Processing :: Markup :: XML
Classifier: Topic :: Utilities
Requires-Python: >=3.9
Requires-Dist: lxml>=4.0
Provides-Extra: docs
Requires-Dist: furo==2025.9.25; extra == 'docs'
Requires-Dist: sphinx~=8.2.3; extra == 'docs'
Provides-Extra: syntax
Requires-Dist: pygments>=2.7; extra == 'syntax'
Provides-Extra: test
Requires-Dist: black~=25.9; extra == 'test'
Requires-Dist: isort~=6.1.0; extra == 'test'
Requires-Dist: lxml-stubs~=0.5.1; extra == 'test'
Requires-Dist: mypy~=1.18.2; extra == 'test'
Requires-Dist: ruff~=0.14.1; extra == 'test'
Requires-Dist: types-pygments~=2.19; extra == 'test'
